PyMAIA/__init__.py
PyMAIA/_version.py
PyMAIA/configs/__init__.py
PyMAIA/monai/__init__.py
PyMAIA/monai/apps/__init__.py
PyMAIA/monai/apps/detection/__init__.py
PyMAIA/monai/apps/detection/networks/__init__.py
PyMAIA/utils/__init__.py
PyMAIA/utils/file_utils.py
PyMAIA/utils/log_utils.py
PyMAIA/utils/seg_mask_utils.py
PyMAIA/utils/volume_utils.py
PyMAIA_scripts/PyMAIA_convert_DICOM_dataset_to_NIFTI_dataset.py
PyMAIA_scripts/PyMAIA_convert_NIFTI_predictions_to_DICOM_SEG.py
PyMAIA_scripts/PyMAIA_convert_semantic_to_instance_segmentation.py
PyMAIA_scripts/PyMAIA_create_subset.py
PyMAIA_scripts/PyMAIA_downsample_modality.py
PyMAIA_scripts/PyMAIA_order_data_folder.py
PyMAIA_scripts/PyMAIA_run_pipeline_from_file.py
PyMAIA_scripts/__init__.py
PyMAIA_scripts/nndet_compute_metric_results.py
PyMAIA_scripts/nndet_create_pipeline.py
PyMAIA_scripts/nndet_extract_experiment_predictions.py
PyMAIA_scripts/nndet_prepare_data_folder.py
PyMAIA_scripts/nndet_run_preprocessing.py
PyMAIA_scripts/nndet_run_training.py
PyMAIA_scripts/nnunet_create_pipeline.py
PyMAIA_scripts/nnunet_prepare_data_folder.py
PyMAIA_scripts/nnunet_run_plan_and_preprocessing.py
PyMAIA_scripts/nnunet_run_preprocessing.py
PyMAIA_scripts/nnunet_run_training.py
PyMAIA_scripts/script_template.py
pymaia_learn-1.2.3.data/data/requirements.txt
pymaia_learn-1.2.3.dist-info/LICENSE
pymaia_learn-1.2.3.dist-info/METADATA
pymaia_learn-1.2.3.dist-info/WHEEL
pymaia_learn-1.2.3.dist-info/entry_points.txt
pymaia_learn-1.2.3.dist-info/top_level.txt
pymaia_learn-1.2.3.dist-info/RECORD
