Metadata-Version: 2.2
Name: pymaia-learn
Version: 1.2.3
Summary: Python Package to support Deep Learning data preparation, pre-processing. training, result visualization and model deployment across different frameworks (nnUNet, nnDetection, MONAI).
Home-page: https://github.com/SimoneBendazzoli93/PyMAIA.git
Author: Bendazzoli Simone
Author-email: simben@kth.se
License: GPLv3
Project-URL: Documentation, https://pymaia.readthedocs.io
Project-URL: Bug Tracker, https://github.com/SimoneBendazzoli93/PyMAIA/issues
Project-URL: Source Code, https://github.com/SimoneBendazzoli93/PyMAIA
Keywords: deep learning,image segmentation,medical image analysis,medical image segmentation,object detection
Platform: OS Independent
Classifier: Intended Audience :: Developers
Classifier: Intended Audience :: Education
Classifier: Intended Audience :: Science/Research
Classifier: Intended Audience :: Healthcare Industry
Classifier: Programming Language :: C++
Classifier: Programming Language :: Python :: 3
Classifier: Programming Language :: Python :: 3.8
Classifier: Programming Language :: Python :: 3.9
Classifier: Programming Language :: Python :: 3.10
Classifier: Topic :: Scientific/Engineering
Classifier: Topic :: Scientific/Engineering :: Artificial Intelligence
Classifier: Topic :: Scientific/Engineering :: Medical Science Apps.
Classifier: Topic :: Scientific/Engineering :: Information Analysis
Classifier: Topic :: Software Development
Classifier: Topic :: Software Development :: Libraries
Classifier: Typing :: Typed
Requires-Python: >=3.8
License-File: LICENSE
Requires-Dist: coloredlogs
Requires-Dist: dicom2nifti
Requires-Dist: nibabel
Requires-Dist: nilearn
Requires-Dist: numpy
Requires-Dist: pydicom
Requires-Dist: pydicom_seg
Requires-Dist: scipy
Requires-Dist: SimpleITK
Requires-Dist: tqdm
Requires-Dist: pandas
Requires-Dist: scikit_learn
Requires-Dist: openpyxl
Requires-Dist: mlflow
Dynamic: keywords
